emzed_ext_test/__init__.py
emzed_ext_test/minimal_module.py
emzed_ext_test/data/readme.txt
emzed_ext_test-0.0.2.dist-info/LICENSE.txt
emzed_ext_test-0.0.2.dist-info/METADATA
emzed_ext_test-0.0.2.dist-info/WHEEL
emzed_ext_test-0.0.2.dist-info/top_level.txt
emzed_ext_test-0.0.2.dist-info/RECORD
