Metadata-Version: 2.1
Name: emzed-ext-test
Version: 0.0.2
Summary: please describe the package here in one line
Home-page: https://biol.ethz.ch
Author: Hans Dampf
Author-email: hans.dampf@biol.ethz.ch
License: http://opensource.org/licenses/GPL-3.0
Platform: UNKNOWN
Requires-Dist: emzed3
Requires-Dist: emzed3-gui
